{
    "name": "AuthModule",
    "alias": "authmodule",
    "authors": [
        {
            "name": "CyanFox-Projects",
            "email": "opensource@cyanfox.de"
        }
    ],
    "keywords": [
        "cyanfox",
        "auth",
        "module"
    ],
    "version": "1.0.2",
    "template_version": "3.x.x",
    "remote_version": "https://raw.githubusercontent.com/CyanFox-Projects/CyanFox-Base-Modules/v3/AuthModule/module.json",
    "description": "An authentication module for CyanFox-Base v3.",
    "settings_page": "admin.modules.settings.authmodule",
    "priority": 0,
    "providers": [
        "Modules\\AuthModule\\Providers\\AuthModuleServiceProvider"
    ],
    "files": []
}
